<?xml version="1.0" encoding="UTF-8" ?>
<resource_file type="PackedScene" subresource_count="6" version="1.1" version_name="Godot Engine v1.1.beta1.custom_build">
	<ext_resource path="res://panel_sign/panel_sign.xml" type="PackedScene"></ext_resource>
	<ext_resource path="res://main_character/lady.xml" type="PackedScene"></ext_resource>
	<ext_resource path="res://main_character/ui/black_panel.png" type="Texture"></ext_resource>
	<ext_resource path="res://non_player_character/hedgehog.xml" type="PackedScene"></ext_resource>
	<resource type="RectangleShape2D" path="local://1">
		<real name="custom_solver_bias"> 0 </real>
		<vector2 name="extents"> 500, 10 </vector2>

	</resource>
	<main_resource>
		<dictionary name="_bundled" shared="false">
			<string> "names" </string>
			<string_array  len="45">
				<string> "MainScene" </string>
				<string> "Node2D" </string>
				<string> "_import_path" </string>
				<string> "visibility/visible" </string>
				<string> "visibility/opacity" </string>
				<string> "visibility/self_opacity" </string>
				<string> "visibility/light_mask" </string>
				<string> "transform/pos" </string>
				<string> "transform/rot" </string>
				<string> "transform/scale" </string>
				<string> "z/z" </string>
				<string> "z/relative" </string>
				<string> "__meta__" </string>
				<string> "Ground" </string>
				<string> "StaticBody2D" </string>
				<string> "input/pickable" </string>
				<string> "shape_count" </string>
				<string> "shapes/0/shape" </string>
				<string> "shapes/0/transform" </string>
				<string> "shapes/0/trigger" </string>
				<string> "layers" </string>
				<string> "constant_linear_velocity" </string>
				<string> "constant_angular_velocity" </string>
				<string> "friction" </string>
				<string> "bounce" </string>
				<string> "Sprite" </string>
				<string> "texture" </string>
				<string> "centered" </string>
				<string> "offset" </string>
				<string> "flip_h" </string>
				<string> "flip_v" </string>
				<string> "vframes" </string>
				<string> "hframes" </string>
				<string> "frame" </string>
				<string> "modulate" </string>
				<string> "region" </string>
				<string> "region_rect" </string>
				<string> "CollisionShape2D" </string>
				<string> "shape" </string>
				<string> "trigger" </string>
				<string> "Lady" </string>
				<string> "RigidBody2D" </string>
				<string> "PanelSign" </string>
				<string> "Area2D" </string>
				<string> "Hedgehog" </string>
			</string_array>
			<string> "version" </string>
			<int> 1 </int>
			<string> "conn_count" </string>
			<int> 0 </int>
			<string> "node_count" </string>
			<int> 7 </int>
			<string> "variants" </string>
			<array  len="28" shared="false">
				<node_path> "" </node_path>
				<bool> True </bool>
				<real> 1 </real>
				<int> 1 </int>
				<vector2> 0, 0 </vector2>
				<real> 0 </real>
				<vector2> 1, 1 </vector2>
				<int> 0 </int>
				<dictionary  shared="false">
					<string> "__editor_plugin_states__" </string>
					<dictionary  shared="false">
						<string> "Script" </string>
						<dictionary  shared="false">
							<string> "current" </string>
							<int> 0 </int>
							<string> "sources" </string>
							<array  len="1" shared="false">
								<string> "res://panel_sign/panel_sign.gd" </string>
							</array>
						</dictionary>
						<string> "2D" </string>
						<dictionary  shared="false">
							<string> "snap_pixel" </string>
							<bool> False </bool>
							<string> "snap_rotation_step" </string>
							<real> 0.261799 </real>
							<string> "zoom" </string>
							<real> 3.090868 </real>
							<string> "snap_step" </string>
							<vector2> 10, 10 </vector2>
							<string> "snap_relative" </string>
							<bool> False </bool>
							<string> "snap_grid" </string>
							<bool> False </bool>
							<string> "snap_rotation_offset" </string>
							<real> 0 </real>
							<string> "snap_show_grid" </string>
							<bool> False </bool>
							<string> "snap_offset" </string>
							<vector2> 0, 0 </vector2>
							<string> "ofs" </string>
							<vector2> 11.0893, 471.067 </vector2>
							<string> "snap_rotation" </string>
							<bool> False </bool>
						</dictionary>
						<string> "3D" </string>
						<dictionary  shared="false">
							<string> "deflight_rot_y" </string>
							<real> 0.628319 </real>
							<string> "zfar" </string>
							<real> 500 </real>
							<string> "fov" </string>
							<real> 45 </real>
							<string> "viewports" </string>
							<array  len="4" shared="false">
								<dictionary  shared="false">
									<string> "distance" </string>
									<real> 4 </real>
									<string> "x_rot" </string>
									<real> 0 </real>
									<string> "y_rot" </string>
									<real> 0 </real>
									<string> "listener" </string>
									<bool> True </bool>
									<string> "use_environment" </string>
									<bool> False </bool>
									<string> "use_orthogonal" </string>
									<bool> False </bool>
									<string> "pos" </string>
									<vector3> 0, 0, 0 </vector3>
								</dictionary>
								<dictionary  shared="false">
									<string> "distance" </string>
									<real> 4 </real>
									<string> "x_rot" </string>
									<real> 0 </real>
									<string> "y_rot" </string>
									<real> 0 </real>
									<string> "listener" </string>
									<bool> False </bool>
									<string> "use_environment" </string>
									<bool> False </bool>
									<string> "use_orthogonal" </string>
									<bool> False </bool>
									<string> "pos" </string>
									<vector3> 0, 0, 0 </vector3>
								</dictionary>
								<dictionary  shared="false">
									<string> "distance" </string>
									<real> 4 </real>
									<string> "x_rot" </string>
									<real> 0 </real>
									<string> "y_rot" </string>
									<real> 0 </real>
									<string> "listener" </string>
									<bool> False </bool>
									<string> "use_environment" </string>
									<bool> False </bool>
									<string> "use_orthogonal" </string>
									<bool> False </bool>
									<string> "pos" </string>
									<vector3> 0, 0, 0 </vector3>
								</dictionary>
								<dictionary  shared="false">
									<string> "distance" </string>
									<real> 4 </real>
									<string> "x_rot" </string>
									<real> 0 </real>
									<string> "y_rot" </string>
									<real> 0 </real>
									<string> "listener" </string>
									<bool> False </bool>
									<string> "use_environment" </string>
									<bool> False </bool>
									<string> "use_orthogonal" </string>
									<bool> False </bool>
									<string> "pos" </string>
									<vector3> 0, 0, 0 </vector3>
								</dictionary>
							</array>
							<string> "viewport_mode" </string>
							<int> 1 </int>
							<string> "default_light" </string>
							<bool> True </bool>
							<string> "ambient_light_color" </string>
							<color> 0.15, 0.15, 0.15, 1 </color>
							<string> "show_grid" </string>
							<bool> True </bool>
							<string> "show_origin" </string>
							<bool> True </bool>
							<string> "znear" </string>
							<real> 0.1 </real>
							<string> "default_srgb" </string>
							<bool> False </bool>
							<string> "deflight_rot_x" </string>
							<real> 0.942478 </real>
						</dictionary>
					</dictionary>
					<string> "__editor_run_settings__" </string>
					<dictionary  shared="false">
						<string> "custom_args" </string>
						<string> "-l $scene" </string>
						<string> "run_mode" </string>
						<int> 0 </int>
					</dictionary>
					<string> "__editor_plugin_screen__" </string>
					<string> "2D" </string>
				</dictionary>
				<vector2> 434.896, 560.738 </vector2>
				<bool> False </bool>
				<resource  resource_type="Shape2D" path="local://1">  </resource>
				<matrix32> 1, 0, 0, 1, 0, 0 </matrix32>
				<dictionary  shared="false">
					<string> "_editor_collapsed" </string>
					<bool> True </bool>
				</dictionary>
				<vector2> 0.824988, 54.5298 </vector2>
				<vector2> 7.79252, 1 </vector2>
				<resource  resource_type="Texture" path="res://main_character/ui/black_panel.png">  </resource>
				<color> 1, 1, 1, 1 </color>
				<rect2> 0, 0, 0, 0 </rect2>
				<resource  resource_type="PackedScene" path="res://main_character/lady.xml">  </resource>
				<vector2> 418.075, 499.235 </vector2>
				<dictionary  shared="false">
					<string> "__editor_plugin_states__" </string>
					<dictionary  shared="false">
						<string> "Script" </string>
						<dictionary  shared="false">
							<string> "current" </string>
							<int> 0 </int>
							<string> "sources" </string>
							<array  len="1" shared="false">
								<string> "res://lady.gd" </string>
							</array>
						</dictionary>
						<string> "2D" </string>
						<dictionary  shared="false">
							<string> "snap_pixel" </string>
							<bool> False </bool>
							<string> "snap_rotation_step" </string>
							<real> 0.261799 </real>
							<string> "snap_step" </string>
							<vector2> 10, 10 </vector2>
							<string> "snap_relative" </string>
							<bool> False </bool>
							<string> "zoom" </string>
							<real> 0.487674 </real>
							<string> "snap_rotation_offset" </string>
							<real> 0 </real>
							<string> "snap_grid" </string>
							<bool> False </bool>
							<string> "snap_show_grid" </string>
							<bool> False </bool>
							<string> "snap_offset" </string>
							<vector2> 0, 0 </vector2>
							<string> "ofs" </string>
							<vector2> -869.377, -463.112 </vector2>
							<string> "snap_rotation" </string>
							<bool> False </bool>
						</dictionary>
						<string> "3D" </string>
						<dictionary  shared="false">
							<string> "fov" </string>
							<real> 45 </real>
							<string> "zfar" </string>
							<real> 500 </real>
							<string> "viewports" </string>
							<array  len="4" shared="false">
								<dictionary  shared="false">
									<string> "distance" </string>
									<real> 4 </real>
									<string> "x_rot" </string>
									<real> 0 </real>
									<string> "y_rot" </string>
									<real> 0 </real>
									<string> "listener" </string>
									<bool> True </bool>
									<string> "use_environment" </string>
									<bool> False </bool>
									<string> "use_orthogonal" </string>
									<bool> False </bool>
									<string> "pos" </string>
									<vector3> 0, 0, 0 </vector3>
								</dictionary>
								<dictionary  shared="false">
									<string> "distance" </string>
									<real> 4 </real>
									<string> "x_rot" </string>
									<real> 0 </real>
									<string> "y_rot" </string>
									<real> 0 </real>
									<string> "listener" </string>
									<bool> False </bool>
									<string> "use_environment" </string>
									<bool> False </bool>
									<string> "use_orthogonal" </string>
									<bool> False </bool>
									<string> "pos" </string>
									<vector3> 0, 0, 0 </vector3>
								</dictionary>
								<dictionary  shared="false">
									<string> "distance" </string>
									<real> 4 </real>
									<string> "x_rot" </string>
									<real> 0 </real>
									<string> "y_rot" </string>
									<real> 0 </real>
									<string> "listener" </string>
									<bool> False </bool>
									<string> "use_environment" </string>
									<bool> False </bool>
									<string> "use_orthogonal" </string>
									<bool> False </bool>
									<string> "pos" </string>
									<vector3> 0, 0, 0 </vector3>
								</dictionary>
								<dictionary  shared="false">
									<string> "distance" </string>
									<real> 4 </real>
									<string> "x_rot" </string>
									<real> 0 </real>
									<string> "y_rot" </string>
									<real> 0 </real>
									<string> "listener" </string>
									<bool> False </bool>
									<string> "use_environment" </string>
									<bool> False </bool>
									<string> "use_orthogonal" </string>
									<bool> False </bool>
									<string> "pos" </string>
									<vector3> 0, 0, 0 </vector3>
								</dictionary>
							</array>
							<string> "deflight_rot_y" </string>
							<real> 0.628319 </real>
							<string> "default_light" </string>
							<bool> True </bool>
							<string> "viewport_mode" </string>
							<int> 1 </int>
							<string> "ambient_light_color" </string>
							<color> 0.15, 0.15, 0.15, 1 </color>
							<string> "show_grid" </string>
							<bool> True </bool>
							<string> "znear" </string>
							<real> 0.1 </real>
							<string> "show_origin" </string>
							<bool> True </bool>
							<string> "deflight_rot_x" </string>
							<real> 0.942478 </real>
							<string> "default_srgb" </string>
							<bool> False </bool>
						</dictionary>
					</dictionary>
					<string> "__editor_run_settings__" </string>
					<dictionary  shared="false">
						<string> "custom_args" </string>
						<string> "-l $scene" </string>
						<string> "run_mode" </string>
						<int> 0 </int>
					</dictionary>
					<string> "__editor_plugin_screen__" </string>
					<string> "2D" </string>
				</dictionary>
				<resource  resource_type="PackedScene" path="res://panel_sign/panel_sign.xml">  </resource>
				<vector2> 758.024, 404.103 </vector2>
				<dictionary  shared="false">
					<string> "__editor_plugin_states__" </string>
					<dictionary  shared="false">
						<string> "2D" </string>
						<dictionary  shared="false">
							<string> "snap_pixel" </string>
							<bool> False </bool>
							<string> "snap_rotation_step" </string>
							<real> 0.261799 </real>
							<string> "snap_step" </string>
							<vector2> 10, 10 </vector2>
							<string> "snap_relative" </string>
							<bool> False </bool>
							<string> "zoom" </string>
							<real> 1.850617 </real>
							<string> "snap_rotation_offset" </string>
							<real> 0 </real>
							<string> "snap_grid" </string>
							<bool> False </bool>
							<string> "snap_show_grid" </string>
							<bool> False </bool>
							<string> "snap_offset" </string>
							<vector2> 0, 0 </vector2>
							<string> "ofs" </string>
							<vector2> -153.549, -106.998 </vector2>
							<string> "snap_rotation" </string>
							<bool> False </bool>
						</dictionary>
						<string> "3D" </string>
						<dictionary  shared="false">
							<string> "fov" </string>
							<real> 45 </real>
							<string> "zfar" </string>
							<real> 500 </real>
							<string> "viewports" </string>
							<array  len="4" shared="false">
								<dictionary  shared="false">
									<string> "distance" </string>
									<real> 4 </real>
									<string> "x_rot" </string>
									<real> 0 </real>
									<string> "y_rot" </string>
									<real> 0 </real>
									<string> "listener" </string>
									<bool> True </bool>
									<string> "use_environment" </string>
									<bool> False </bool>
									<string> "use_orthogonal" </string>
									<bool> False </bool>
									<string> "pos" </string>
									<vector3> 0, 0, 0 </vector3>
								</dictionary>
								<dictionary  shared="false">
									<string> "distance" </string>
									<real> 4 </real>
									<string> "x_rot" </string>
									<real> 0 </real>
									<string> "y_rot" </string>
									<real> 0 </real>
									<string> "listener" </string>
									<bool> False </bool>
									<string> "use_environment" </string>
									<bool> False </bool>
									<string> "use_orthogonal" </string>
									<bool> False </bool>
									<string> "pos" </string>
									<vector3> 0, 0, 0 </vector3>
								</dictionary>
								<dictionary  shared="false">
									<string> "distance" </string>
									<real> 4 </real>
									<string> "x_rot" </string>
									<real> 0 </real>
									<string> "y_rot" </string>
									<real> 0 </real>
									<string> "listener" </string>
									<bool> False </bool>
									<string> "use_environment" </string>
									<bool> False </bool>
									<string> "use_orthogonal" </string>
									<bool> False </bool>
									<string> "pos" </string>
									<vector3> 0, 0, 0 </vector3>
								</dictionary>
								<dictionary  shared="false">
									<string> "distance" </string>
									<real> 4 </real>
									<string> "x_rot" </string>
									<real> 0 </real>
									<string> "y_rot" </string>
									<real> 0 </real>
									<string> "listener" </string>
									<bool> False </bool>
									<string> "use_environment" </string>
									<bool> False </bool>
									<string> "use_orthogonal" </string>
									<bool> False </bool>
									<string> "pos" </string>
									<vector3> 0, 0, 0 </vector3>
								</dictionary>
							</array>
							<string> "deflight_rot_y" </string>
							<real> 0.628319 </real>
							<string> "default_light" </string>
							<bool> True </bool>
							<string> "viewport_mode" </string>
							<int> 1 </int>
							<string> "ambient_light_color" </string>
							<color> 0.15, 0.15, 0.15, 1 </color>
							<string> "show_grid" </string>
							<bool> True </bool>
							<string> "znear" </string>
							<real> 0.1 </real>
							<string> "show_origin" </string>
							<bool> True </bool>
							<string> "deflight_rot_x" </string>
							<real> 0.942478 </real>
							<string> "default_srgb" </string>
							<bool> False </bool>
						</dictionary>
					</dictionary>
					<string> "__editor_run_settings__" </string>
					<dictionary  shared="false">
						<string> "custom_args" </string>
						<string> "-l $scene" </string>
						<string> "run_mode" </string>
						<int> 0 </int>
					</dictionary>
					<string> "__editor_plugin_screen__" </string>
					<string> "2D" </string>
				</dictionary>
				<resource  resource_type="PackedScene" path="res://non_player_character/hedgehog.xml">  </resource>
				<vector2> 73.4538, 391.677 </vector2>
				<dictionary  shared="false">
					<string> "__editor_plugin_states__" </string>
					<dictionary  shared="false">
						<string> "Script" </string>
						<dictionary  shared="false">
							<string> "current" </string>
							<int> 0 </int>
							<string> "sources" </string>
							<array  len="2" shared="false">
								<string> "res://non_player_character/hedgehog.gd" </string>
								<string> "res://panel_sign/panel_sign.gd" </string>
							</array>
						</dictionary>
						<string> "2D" </string>
						<dictionary  shared="false">
							<string> "snap_pixel" </string>
							<bool> False </bool>
							<string> "snap_rotation_step" </string>
							<real> 0.261799 </real>
							<string> "snap_relative" </string>
							<bool> False </bool>
							<string> "zoom" </string>
							<real> 1.108034 </real>
							<string> "snap_step" </string>
							<vector2> 10, 10 </vector2>
							<string> "snap_grid" </string>
							<bool> False </bool>
							<string> "snap_rotation_offset" </string>
							<real> 0 </real>
							<string> "snap_show_grid" </string>
							<bool> False </bool>
							<string> "snap_offset" </string>
							<vector2> 0, 0 </vector2>
							<string> "ofs" </string>
							<vector2> -375.547, -169.352 </vector2>
							<string> "snap_rotation" </string>
							<bool> False </bool>
						</dictionary>
						<string> "3D" </string>
						<dictionary  shared="false">
							<string> "viewports" </string>
							<array  len="4" shared="false">
								<dictionary  shared="false">
									<string> "distance" </string>
									<real> 4 </real>
									<string> "x_rot" </string>
									<real> 0 </real>
									<string> "y_rot" </string>
									<real> 0 </real>
									<string> "listener" </string>
									<bool> True </bool>
									<string> "use_environment" </string>
									<bool> False </bool>
									<string> "use_orthogonal" </string>
									<bool> False </bool>
									<string> "pos" </string>
									<vector3> 0, 0, 0 </vector3>
								</dictionary>
								<dictionary  shared="false">
									<string> "distance" </string>
									<real> 4 </real>
									<string> "x_rot" </string>
									<real> 0 </real>
									<string> "y_rot" </string>
									<real> 0 </real>
									<string> "listener" </string>
									<bool> False </bool>
									<string> "use_environment" </string>
									<bool> False </bool>
									<string> "use_orthogonal" </string>
									<bool> False </bool>
									<string> "pos" </string>
									<vector3> 0, 0, 0 </vector3>
								</dictionary>
								<dictionary  shared="false">
									<string> "distance" </string>
									<real> 4 </real>
									<string> "x_rot" </string>
									<real> 0 </real>
									<string> "y_rot" </string>
									<real> 0 </real>
									<string> "listener" </string>
									<bool> False </bool>
									<string> "use_environment" </string>
									<bool> False </bool>
									<string> "use_orthogonal" </string>
									<bool> False </bool>
									<string> "pos" </string>
									<vector3> 0, 0, 0 </vector3>
								</dictionary>
								<dictionary  shared="false">
									<string> "distance" </string>
									<real> 4 </real>
									<string> "x_rot" </string>
									<real> 0 </real>
									<string> "y_rot" </string>
									<real> 0 </real>
									<string> "listener" </string>
									<bool> False </bool>
									<string> "use_environment" </string>
									<bool> False </bool>
									<string> "use_orthogonal" </string>
									<bool> False </bool>
									<string> "pos" </string>
									<vector3> 0, 0, 0 </vector3>
								</dictionary>
							</array>
							<string> "zfar" </string>
							<real> 500 </real>
							<string> "deflight_rot_y" </string>
							<real> 0.628319 </real>
							<string> "fov" </string>
							<real> 45 </real>
							<string> "viewport_mode" </string>
							<int> 1 </int>
							<string> "default_light" </string>
							<bool> True </bool>
							<string> "ambient_light_color" </string>
							<color> 0.15, 0.15, 0.15, 1 </color>
							<string> "show_grid" </string>
							<bool> True </bool>
							<string> "show_origin" </string>
							<bool> True </bool>
							<string> "znear" </string>
							<real> 0.1 </real>
							<string> "default_srgb" </string>
							<bool> False </bool>
							<string> "deflight_rot_x" </string>
							<real> 0.942478 </real>
						</dictionary>
					</dictionary>
					<string> "__editor_run_settings__" </string>
					<dictionary  shared="false">
						<string> "custom_args" </string>
						<string> "-l $scene" </string>
						<string> "run_mode" </string>
						<int> 0 </int>
					</dictionary>
					<string> "__editor_plugin_screen__" </string>
					<string> "Script" </string>
				</dictionary>
			</array>
			<string> "nodes" </string>
			<int_array  len="197"> 				-1, -1, 1, 0, -1, 11, 2, 0, 3, 1, 4, 2, 5, 2, 6, 3, 7, 4, 8, 5, 9, 6, 10, 7, 11, 1, 12, 8, 0, 0, 0, 14, 13, -1, 21, 2, 0, 3, 1, 4, 2, 5, 2, 6, 3, 7, 9, 8, 5, 9, 6, 10, 7, 11, 1, 15, 10, 16, 3, 17, 11, 18, 12, 19, 10, 20, 3, 21, 4, 22, 5, 23, 2, 24, 5, 12, 13, 0, 1, 0, 25, 25, -1, 21, 2, 0, 3, 1, 4, 2, 5, 2, 6, 3, 7, 14, 8, 5, 9, 15, 10, 7, 11, 1, 26, 16, 27, 1, 28, 4, 29, 10, 30, 10, 31, 3, 32, 3, 33, 7, 34, 17, 35, 10, 36, 18, 0, 1, 0, 37, 37, -1, 12, 2, 0, 3, 1, 4, 2, 5, 2, 6, 3, 7, 4, 8, 5, 9, 6, 10, 7, 11, 1, 38, 11, 39, 10, 0, 0, 0, 41, 40, 19, 3, 2, 0, 7, 20, 12, 21, 0, 0, 0, 43, 42, 22, 3, 2, 0, 7, 23, 12, 24, 0, 0, 0, 43, 44, 25, 3, 2, 0, 7, 26, 12, 27, 0 </int_array>
			<string> "conns" </string>
			<int_array  len="0"> 				 </int_array>
		</dictionary>

	</main_resource>
</resource_file>